{
    "meta": {
		"formtype": "HEALTH INSURANCE CLAIM FORM"
	},
	"PATIENT AND INSURED INFORMATION": [
		{
			"1.INSURED PLAN": "MEDIACARE Medicare#",
			"1a. INSURED'S I.D. NUMBER": "GET732564-9788",
			"2. PATIENT'S NAME": "CHAD, STEPHENS C",
			"3. PATIENT'S DATE OF BIRTH":[
			{"MM":"12", "DD":"08", "YY":"1970"}
			],
			"3. PATIENT'S SEX": "M",
			"4. INSURED'S NAME": "STEPHENS, SAMANTHA ",
			"5. PATIENT'S ADDRESS": "3021 W SOUTHLAKE BLVD",
			"5. PATIENT'S CITY": "SOUTH LAKE",
			"5. PATIENT'S STATE":"SD",
			"5. PATIENT'S ZIP CODE": "76092",
			"5. PATIENT'S TELEPHONE": "833 306-9981",
			"6. PATIENT RELATIONSHIP": "Other",
			"7. INSURED'S ADDRESS": " ",
			"7. INSURED'S CITY": "SOUTH LAKE", 
			"7. INSURED'S STATE":"SD",
			"7. INSURED'S ZIP CODE":"76092", 
			"7. INSURED'S TELEPHONE":"765 235 - 5916",
			"9. OTHER INSURED'S NAME": "STEPHENS, SAMANTHA ",
			"9a. OTHER INSURED'S POLICY OR GROUP": "40819019926",
			"9d. INSURANCE PLAN NAME": "MEDICARE PRIMARY",
			"10. PATIENT'S CONDITION": [
			{"10a. EMPLOYMENT": "NO"},
			{"10b. AUTO ACCIDENT": "NO"},
			{"10c. OTHER ACCIDENT":"YES"}
			],
			"11. INSURED'S POLICY GROUP OR FECA NUMBER": "1144231",
			"11a. INSURED'S SEX": "F",
			"11c. INSURANCE PLAN NAME": "GLEN'S MEDICAID SOCIETY PPO",
			"11d. IS THERE ANOTHER HEALTH BENEFIT PLAN": "NO",
			"12. PATIENT'S OR AUTHORIZED PERSON'S SIGNATURE": [
			{"SIGNED": "SIGNATURE ON FILE", "DATE": "01/17/2024"}
			],
			"13. INSURED OR AUTHORIZED PERSON'S SIGNATURE": "SIGNATURE ON FILE"
		}
	],
	"PHYSICIAN OR MEDICAL PROVIDER INFORMATION": [
        {
            "21. DIAGNOSIS OR NATURE OF ILLNESS": [
			{
				"label":"ICD Indicator",
				"text": "9",
				"words": [
					{
						"word": "9",
						"normalizedVertices": [
							{
								"x": 875,
								"y": 1295
							},
							{
								"x": 905,
								"y": 1295
							},
							{
								"x": 905,
								"y": 1320
							},
							{
								"x": 875,
								"y": 1320
							}
						]
					}
				]	
			},
			{"ILLNESS A.": "RX2145", "ILLNESS B.": "S8994", "ILLNESS C.": "", "ILLNESS D.": "JD9119"},
			{"ILLNESS E.": "", "ILLNESS F.": "E188 . 3"}
			],
			"20. OUTSIDE LAB": "NO",
			"20. LAB $CHARGES": "0|00",
			"22. RESUBMISSION CODE": "S 06",
			"23. PRIOR AUTHORIZATION NUMBER": "35648521022",
			"24. SERVICES": [
			{"MM 1":"11", "DD 1":"03", "YY 1": "22", "PLACE OF SERVICE 1": "11", "EMG 1": "Y", "CPT/HCPCS 1": "K2356", "MODIFIER 1": "CG", "DIAGNOSIS POINTER 1": "A23", "$CHARGES 1":"39|21", "UNITS 1":"1.5", "Family Plan 1": "Y", "PROVIDER ID 1": ""},
			{"MM 2":"15", "DD 2":"09", "YY 2":"24", "PLACE OF SERVICE 2": "12", "EMG 2": "Y", "CPT/HCPCS 2": "93557", "MODIFIER 2": "NU", "DIAGNOSIS POINTER 2": "AA14", "$CHARGES 2": "421|95", "UNITS 2": "95", "Family Plan 2": "", "PROVIDER ID 2": "256632458084"},
			{"MM 3":"06", "DD 3":"05", "YY 3":"21", "PLACE OF SERVICE 3": "10", "EMG 3": "", "CPT/HCPCS 3": "R7789.0", "MODIFIER 3": "28", "DIAGNOSIS POINTER 3": "AB", "$CHARGES 3": "632|80", "UNITS 3": "007", "Family Plan 3": "", "PROVIDER ID 3": "256632458084"}
			],
			"25. FEDERAL TAX I.D. NUMBER": "457-30-6881",
			"25. FEDERAL IDENTIFICATION": "X SSN",
            "26. PATIENT'S ACCOUNT NUMBER": "90056214612",
            "27. ACCEPT ASSIGNMENT": "YES",
			"28. TOTAL CHARGE": "1093|96",
			"29. AMOUNT PAID": "1090|00",
			"31. PHYSICIAN OR SUPPLIER SIGNATURE": [
			{"SIGNED": "SIGNATURE ON FILE", "DATE": "12/01/2022"}
			],
			"32. SERVICE INFORMATION": [
			{"32. SERVICE FACILITY LOCATION": "DR KIM'S DENTAL CARE CLINIC MEDICAL CENTRE 21ST TOWER BLOCK, IL 875886 HARVEY CROWN, 32ND AVENUE"},
			{"32. a. NPI NUMBER": "256632458084"}
			],
			"33. BILLING INFORMATION": [
			{"33. BILLING PROVIDER PHONE": "555 838 - 7339"},
			{"33. BILLING PROVIDER LOCATION": "PAY TO: HCC BILLING SECTION XI XING HEIGHTS, CA 01211 PO BOX 60115"},
			{"33. a. NPI NUMBER": ""}
			]
		}
	]
}